README.md
setup.cfg
setup.py
distributions_fidan_2/Binomialdistribution.py
distributions_fidan_2/Gaussiandistribution.py
distributions_fidan_2/Generaldistribution.py
distributions_fidan_2/__init__.py
distributions_fidan_2.egg-info/PKG-INFO
distributions_fidan_2.egg-info/SOURCES.txt
distributions_fidan_2.egg-info/dependency_links.txt
distributions_fidan_2.egg-info/not-zip-safe
distributions_fidan_2.egg-info/top_level.txt